{
   "html_attributions" : [],
   "results" : 
   [
      {
         "business_status" : "OPERATIONAL",
         "formatted_address" : "46MM+9Q2, Cross Island Rd, Apia, Samoa",
         "geometry" : 
         {
            "location" : 
            {
               "lat" : -13.8664954,
               "lng" : -171.7655603
            },
            "viewport" : 
            {
               "northeast" : 
               {
                  "lat" : -13.86519132010728,
                  "lng" : -171.7642278701073
               },
               "southwest" : 
               {
                  "lat" : -13.86789097989272,
                  "lng" : -171.7669275298927
               }
            }
         },
         "icon" : "https://maps.gstatic.com/mapfiles/place_api/icons/v1/png_71/museum-71.png",
         "icon_background_color" : "#13B5C7",
         "icon_mask_base_uri" : "https://maps.gstatic.com/mapfiles/place_api/icons/v2/museum_pinlet",
         "name" : "Robert Louis Stevenson Museum",
         "opening_hours" : 
         {
            "open_now" : false
         },
         "photos" : 
         [
            {
               "height" : 1080,
               "html_attributions" : 
               [
                  "\u003ca href=\"https://maps.google.com/maps/contrib/101635688474323435710\"\u003eTom Boneahawk\u003c/a\u003e"
               ],
               "photo_reference" : "ATplDJZ6Q4bif-okc5UCr440Zldv0MuBG4_bQaZplR5pe4BRBuN0lIuUZO5iIr8gfKzWu8LOoXqD5IfDRVdVAmZ6KpnASIQ1PKJrDwiPM-3oEkRDL6Z0ItgqhJogl1ImUxL2o-Pe9CMk5NM-heKW0yBdzxZJwKjoX8J6IzRloKq2Cv9gxoKF",
               "width" : 1080
            }
         ],
         "place_id" : "ChIJ3-n9l48TpXERygbQP2r8KSU",
         "rating" : 4.7,
         "reference" : "ChIJ3-n9l48TpXERygbQP2r8KSU",
         "types" : 
         [
            "museum",
            "point_of_interest",
            "establishment"
         ],
         "user_ratings_total" : 110
      },
      {
         "business_status" : "OPERATIONAL",
         "formatted_address" : "Ififi St, Apia, Samoa",
         "geometry" : 
         {
            "location" : 
            {
               "lat" : -13.8404124,
               "lng" : -171.7630005
            },
            "viewport" : 
            {
               "northeast" : 
               {
                  "lat" : -13.83907682010727,
                  "lng" : -171.7618494701073
               },
               "southwest" : 
               {
                  "lat" : -13.84177647989272,
                  "lng" : -171.7645491298927
               }
            }
         },
         "icon" : "https://maps.gstatic.com/mapfiles/place_api/icons/v1/png_71/museum-71.png",
         "icon_background_color" : "#13B5C7",
         "icon_mask_base_uri" : "https://maps.gstatic.com/mapfiles/place_api/icons/v2/museum_pinlet",
         "name" : "Museum of Samoa",
         "opening_hours" : 
         {
            "open_now" : false
         },
         "photos" : 
         [
            {
               "height" : 3456,
               "html_attributions" : 
               [
                  "\u003ca href=\"https://maps.google.com/maps/contrib/116006485979733048776\"\u003eM N\u003c/a\u003e"
               ],
               "photo_reference" : "ATplDJb6CKF-aobc9dnO9FGEru9phty4yeLinmEPw1WzsvxfHfRMuA7kAtjtYd5LHN6kwrlREL_qQb6ayYFEgMVJyzYu2L7-X2bQBAo-fMvCxe2Mbeh5sTW3ZnlITMqR5XNAj94ZZSj9Z1DJ_yMN3rC7auxC5SvKVIi5859GEN5uG1HLyt8h",
               "width" : 4608
            }
         ],
         "place_id" : "ChIJp4fD4pMTpXERwn5ryXqjCJg",
         "plus_code" : 
         {
            "compound_code" : "565P+RQ Apia, Samoa",
            "global_code" : "52RC565P+RQ"
         },
         "rating" : 3.7,
         "reference" : "ChIJp4fD4pMTpXERwn5ryXqjCJg",
         "types" : 
         [
            "museum",
            "tourist_attraction",
            "point_of_interest",
            "establishment"
         ],
         "user_ratings_total" : 32
      },
      {
         "business_status" : "OPERATIONAL",
         "formatted_address" : "Malua, Samoa",
         "geometry" : 
         {
            "location" : 
            {
               "lat" : -13.8007117,
               "lng" : -171.9051232
            },
            "viewport" : 
            {
               "northeast" : 
               {
                  "lat" : -13.79886662010728,
                  "lng" : -171.9039130701073
               },
               "southwest" : 
               {
                  "lat" : -13.80156627989272,
                  "lng" : -171.9066127298927
               }
            }
         },
         "icon" : "https://maps.gstatic.com/mapfiles/place_api/icons/v1/png_71/museum-71.png",
         "icon_background_color" : "#13B5C7",
         "icon_mask_base_uri" : "https://maps.gstatic.com/mapfiles/place_api/icons/v2/museum_pinlet",
         "name" : "EFKS Fine Art Museum",
         "opening_hours" : 
         {
            "open_now" : false
         },
         "photos" : 
         [
            {
               "height" : 4032,
               "html_attributions" : 
               [
                  "\u003ca href=\"https://maps.google.com/maps/contrib/111556072894619079794\"\u003echris hamling\u003c/a\u003e"
               ],
               "photo_reference" : "ATplDJaXDEobRF6TdY8y8-UNjr0z0MZXiiyi1J6mfC4lQ0lNU-5ZIHRmPphiTauAqnq7NLyyIV4LUKe9yX5sXhMBeu_bBIzDx81YH_OWUSxVYOALnDJ-dZyaMEIxcCDCjpXibtnJyx4pVVuIGxwWMRLk4zDlBxbshB06NvXZzZlP90gtBxRV",
               "width" : 3024
            }
         ],
         "place_id" : "ChIJF3-J2p4_pXERkIE_uoazCqw",
         "plus_code" : 
         {
            "compound_code" : "53XV+PX Malua, Samoa",
            "global_code" : "52RC53XV+PX"
         },
         "rating" : 4.5,
         "reference" : "ChIJF3-J2p4_pXERkIE_uoazCqw",
         "types" : 
         [
            "museum",
            "tourist_attraction",
            "point_of_interest",
            "establishment"
         ],
         "user_ratings_total" : 8
      },
      {
         "business_status" : "OPERATIONAL",
         "formatted_address" : "55FP+97X, Poumuli Street, Apia, Samoa",
         "geometry" : 
         {
            "location" : 
            {
               "lat" : -13.8265182,
               "lng" : -171.8142547
            },
            "viewport" : 
            {
               "northeast" : 
               {
                  "lat" : -13.82509972010728,
                  "lng" : -171.8129753201073
               },
               "southwest" : 
               {
                  "lat" : -13.82779937989272,
                  "lng" : -171.8156749798927
               }
            }
         },
         "icon" : "https://maps.gstatic.com/mapfiles/place_api/icons/v1/png_71/museum-71.png",
         "icon_background_color" : "#13B5C7",
         "icon_mask_base_uri" : "https://maps.gstatic.com/mapfiles/place_api/icons/v2/museum_pinlet",
         "name" : "B.E.N SCULPTURE PARK & ACADEMY OF FINE ARTS",
         "opening_hours" : 
         {
            "open_now" : false
         },
         "photos" : 
         [
            {
               "height" : 3456,
               "html_attributions" : 
               [
                  "\u003ca href=\"https://maps.google.com/maps/contrib/106395759368540935745\"\u003eErnesto Penehuro\u003c/a\u003e"
               ],
               "photo_reference" : "ATplDJY9aoAOYoYdTw1oKPtH-eQg6zbDJZa3wCdqDsRxPX_odLhgIcZfHNfrNXQyvWuQDzR6u27-J7oM18571MvBLyPJBWPxVm-06iP8xZzmUGtreFIe-4g2TMTz4DnY_H5c41q6IIDfdi17dCGrV6XerXcK5BlEPGvjco8F09UsSfLLAoI3",
               "width" : 4608
            }
         ],
         "place_id" : "ChIJjfe3ZUYVpXERzYoapiz6iOw",
         "rating" : 0,
         "reference" : "ChIJjfe3ZUYVpXERzYoapiz6iOw",
         "types" : 
         [
            "museum",
            "point_of_interest",
            "establishment"
         ],
         "user_ratings_total" : 0
      },
      {
         "business_status" : "OPERATIONAL",
         "formatted_address" : "37P3+XPH, Apia, Samoa",
         "geometry" : 
         {
            "location" : 
            {
               "lat" : -13.9125569,
               "lng" : -171.7456269
            },
            "viewport" : 
            {
               "northeast" : 
               {
                  "lat" : -13.91120707010728,
                  "lng" : -171.7442770701072
               },
               "southwest" : 
               {
                  "lat" : -13.91390672989272,
                  "lng" : -171.7469767298927
               }
            }
         },
         "icon" : "https://maps.gstatic.com/mapfiles/place_api/icons/v1/png_71/museum-71.png",
         "icon_background_color" : "#13B5C7",
         "icon_mask_base_uri" : "https://maps.gstatic.com/mapfiles/place_api/icons/v2/museum_pinlet",
         "name" : "Le-Fale-O-Le-Fe'e (Samoan megalithic pre-historical landmark)",
         "photos" : 
         [
            {
               "height" : 2160,
               "html_attributions" : 
               [
                  "\u003ca href=\"https://maps.google.com/maps/contrib/108271834513360728806\"\u003eVaughan Hunt\u003c/a\u003e"
               ],
               "photo_reference" : "ATplDJYRBymmhvWN3spqCriCCEUbDgOSiTAsoBoBR4EY4YyuGgSkKuz-Zzkn8YOUDcYGLs8hx2cGeyye-wa3Nkt-tfZnPFBI8eoEzI9hKwtUfFKraGGoxzBXTktAdlZ5BWw9ZcWLYKcQlChb37QKdmcvV3FqHKuJdLbX0Yv0qm2s2QoO2-LD",
               "width" : 3840
            }
         ],
         "place_id" : "ChIJbQe0mVoRpXERrHfseHPdQes",
         "rating" : 2.3,
         "reference" : "ChIJbQe0mVoRpXERrHfseHPdQes",
         "types" : 
         [
            "museum",
            "point_of_interest",
            "establishment"
         ],
         "user_ratings_total" : 3
      }
   ],
   "status" : "OK"
}